[
    {
        "id": 1,
        "image": "require('./assets/cover/this-that.png')",
        "name":"this-that",
        "technologies": "tech here",
        "description": "A social bracket that lets people choose options",
        "code": "https://github.com/bgswilde/thisthat",
        "link": "https://this--that.herokuapp.com/"
    },
    {
        "id": 2,
        "image": "require('./assets/cover/animal-app.png')",
        "name":"animal-app",
        "technologies": "tech here",
        "description": "A social bracket that lets people choose options",
        "code": "https://ratalla816.github.io/animal-app/",
        "link": "https://cryptic-lowlands-80543.herokuapp.com/"
    },
    {
        "id": 3,
        "image": "require('./assets/cover/note-taker.png')",
        "name":"note-taker",
        "technologies": "tech here",
        "description": "A social bracket that lets people choose options",
        "code": "https://github.com/georgedmendoza/note-taker",
        "link": "https://cryptic-lowlands-80543.herokuapp.com/"
    },
    {
        "id": 4,
        "image": "require('./assets/cover/budget-tracker.png')",
        "name":"budget-tracker",
        "technologies": "tech here",
        "description": "A social bracket that lets people choose options",
        "code": "https://github.com/georgedmendoza/budget-tracker",
        "link": "https://budget1--tracker.herokuapp.com/"
    },
    {
        "id": 5,
        "image": "require('./assets/cover/tech-blog.png')",
        "name":"tech-blog",
        "technologies": "tech here",
        "description": "A social bracket that lets people choose options",
        "code": "https://github.com/georgedmendoza/tech-blog",
        "link": "https://immense-headland-57964.herokuapp.com/" 
    },
    {
        "id": 6,
        "image": "require('./assets/cover/work-day-scheduler')",
        "name":"work-day-scheduler",
        "technologies": "tech here",
        "description": "A social bracket that lets people choose options",
        "code": "https://georgedmendoza.github.io/work-day-scheduler/",
        "link": "https://github.com/georgedmendoza/work-day-scheduler"
    }
]
